simplecalculator0001/__init__.py
simplecalculator0001/calculator.py
simplecalculator0001/tests/__init__.py
simplecalculator0001/tests/tests.py
simplecalculator0001-0.3.dist-info/METADATA
simplecalculator0001-0.3.dist-info/WHEEL
simplecalculator0001-0.3.dist-info/top_level.txt
simplecalculator0001-0.3.dist-info/RECORD
