Metadata-Version: 2.1
Name: simplecalculator0001
Version: 0.3
Summary: Simple Calculator to add, subtract, multiply, divide, exponentiate and take the n root
Author: Renato Mariano
Author-email: relucasmariano@gmail.com
